{
    "header": 600,
    "bgnlib": [
        {
            "time": [
                2019,
                1,
                1,
                0,
                0,
                0,
                2019,
                1,
                1,
                0,
                0,
                0
            ],
            "libname": "pcell",
            "units": [
                1e-09,
                1e-09
            ],
            "bgnstr": [
                {
                    "time": [
                        2019,
                        1,
                        1,
                        0,
                        0,
                        0,
                        2019,
                        1,
                        1,
                        0,
                        0,
                        0
                    ],
                    "strname": "DCL_PMOS_S_70252776_X1_Y3",
                    "elements": [
                        {
                            "type": "boundary",
                            "layer": 94,
                            "datatype": 20,
                            "xy": [
                                0,
                                0,
                                0,
                                17640,
                                2580,
                                17640,
                                2580,
                                0,
                                0,
                                0
                            ]
                        },
                        {
                            "type": "boundary",
                            "layer": 64,
                            "datatype": 20,
                            "xy": [
                                0,
                                0,
                                0,
                                19320,
                                2580,
                                19320,
                                2580,
                                0,
                                0,
                                0
                            ]
                        },
                        {
                            "type": "boundary",
                            "layer": 93,
                            "datatype": 44,
                            "xy": [
                                0,
                                17640,
                                0,
                                19320,
                                2580,
                                19320,
                                2580,
                                17640,
                                0,
                                17640
                            ]
                        },
                        {
                            "type": "boundary",
                            "layer": 67,
                            "datatype": 20,
                            "xy": [
                                1165,
                                335,
                                1165,
                                3865,
                                1415,
                                3865,
                                1415,
                                335,
                                1165,
                                335
                            ]
                        },
                        {
                            "type": "boundary",
                            "layer": 67,
                            "datatype": 20,
                            "xy": [
                                1165,
                                4115,
                                1165,
                                5125,
                                1415,
                                5125,
                                1415,
                                4115,
                                1165,
                                4115
                            ]
                        },
                        {
                            "type": "boundary",
                            "layer": 67,
                            "datatype": 20,
                            "xy": [
                                1165,
                                6215,
                                1165,
                                9745,
                                1415,
                                9745,
                                1415,
                                6215,
                                1165,
                                6215
                            ]
                        },
                        {
                            "type": "boundary",
                            "layer": 67,
                            "datatype": 20,
                            "xy": [
                                1165,
                                9995,
                                1165,
                                11005,
                                1415,
                                11005,
                                1415,
                                9995,
                                1165,
                                9995
                            ]
                        },
                        {
                            "type": "boundary",
                            "layer": 67,
                            "datatype": 20,
                            "xy": [
                                1165,
                                12095,
                                1165,
                                15625,
                                1415,
                                15625,
                                1415,
                                12095,
                                1165,
                                12095
                            ]
                        },
                        {
                            "type": "boundary",
                            "layer": 67,
                            "datatype": 20,
                            "xy": [
                                1165,
                                15875,
                                1165,
                                16885,
                                1415,
                                16885,
                                1415,
                                15875,
                                1165,
                                15875
                            ]
                        },
                        {
                            "type": "boundary",
                            "layer": 67,
                            "datatype": 20,
                            "xy": [
                                1165,
                                17975,
                                1165,
                                18985,
                                1415,
                                18985,
                                1415,
                                17975,
                                1165,
                                17975
                            ]
                        },
                        {
                            "type": "boundary",
                            "layer": 67,
                            "datatype": 20,
                            "xy": [
                                735,
                                335,
                                735,
                                3865,
                                985,
                                3865,
                                985,
                                335,
                                735,
                                335
                            ]
                        },
                        {
                            "type": "boundary",
                            "layer": 67,
                            "datatype": 20,
                            "xy": [
                                735,
                                6215,
                                735,
                                9745,
                                985,
                                9745,
                                985,
                                6215,
                                735,
                                6215
                            ]
                        },
                        {
                            "type": "boundary",
                            "layer": 67,
                            "datatype": 20,
                            "xy": [
                                735,
                                12095,
                                735,
                                15625,
                                985,
                                15625,
                                985,
                                12095,
                                735,
                                12095
                            ]
                        },
                        {
                            "type": "boundary",
                            "layer": 67,
                            "datatype": 20,
                            "xy": [
                                1595,
                                335,
                                1595,
                                3865,
                                1845,
                                3865,
                                1845,
                                335,
                                1595,
                                335
                            ]
                        },
                        {
                            "type": "boundary",
                            "layer": 67,
                            "datatype": 20,
                            "xy": [
                                1595,
                                6215,
                                1595,
                                9745,
                                1845,
                                9745,
                                1845,
                                6215,
                                1595,
                                6215
                            ]
                        },
                        {
                            "type": "boundary",
                            "layer": 67,
                            "datatype": 20,
                            "xy": [
                                1595,
                                12095,
                                1595,
                                15625,
                                1845,
                                15625,
                                1845,
                                12095,
                                1595,
                                12095
                            ]
                        },
                        {
                            "type": "boundary",
                            "layer": 68,
                            "datatype": 20,
                            "xy": [
                                260,
                                4480,
                                260,
                                4760,
                                1460,
                                4760,
                                1460,
                                4480,
                                260,
                                4480
                            ]
                        },
                        {
                            "type": "boundary",
                            "layer": 68,
                            "datatype": 20,
                            "xy": [
                                260,
                                280,
                                260,
                                560,
                                1460,
                                560,
                                1460,
                                280,
                                260,
                                280
                            ]
                        },
                        {
                            "type": "boundary",
                            "layer": 68,
                            "datatype": 20,
                            "xy": [
                                690,
                                700,
                                690,
                                980,
                                1890,
                                980,
                                1890,
                                700,
                                690,
                                700
                            ]
                        },
                        {
                            "type": "boundary",
                            "layer": 68,
                            "datatype": 20,
                            "xy": [
                                260,
                                10360,
                                260,
                                10640,
                                1460,
                                10640,
                                1460,
                                10360,
                                260,
                                10360
                            ]
                        },
                        {
                            "type": "boundary",
                            "layer": 68,
                            "datatype": 20,
                            "xy": [
                                260,
                                6160,
                                260,
                                6440,
                                1460,
                                6440,
                                1460,
                                6160,
                                260,
                                6160
                            ]
                        },
                        {
                            "type": "boundary",
                            "layer": 68,
                            "datatype": 20,
                            "xy": [
                                690,
                                6580,
                                690,
                                6860,
                                1890,
                                6860,
                                1890,
                                6580,
                                690,
                                6580
                            ]
                        },
                        {
                            "type": "boundary",
                            "layer": 68,
                            "datatype": 20,
                            "xy": [
                                260,
                                16240,
                                260,
                                16520,
                                1460,
                                16520,
                                1460,
                                16240,
                                260,
                                16240
                            ]
                        },
                        {
                            "type": "boundary",
                            "layer": 68,
                            "datatype": 20,
                            "xy": [
                                260,
                                12040,
                                260,
                                12320,
                                1460,
                                12320,
                                1460,
                                12040,
                                260,
                                12040
                            ]
                        },
                        {
                            "type": "boundary",
                            "layer": 68,
                            "datatype": 20,
                            "xy": [
                                690,
                                18340,
                                690,
                                18620,
                                1890,
                                18620,
                                1890,
                                18340,
                                690,
                                18340
                            ]
                        },
                        {
                            "type": "boundary",
                            "layer": 68,
                            "datatype": 20,
                            "xy": [
                                690,
                                12460,
                                690,
                                12740,
                                1890,
                                12740,
                                1890,
                                12460,
                                690,
                                12460
                            ]
                        },
                        {
                            "type": "boundary",
                            "layer": 67,
                            "datatype": 44,
                            "xy": [
                                1205,
                                335,
                                1205,
                                505,
                                1375,
                                505,
                                1375,
                                335,
                                1205,
                                335
                            ]
                        },
                        {
                            "type": "boundary",
                            "layer": 67,
                            "datatype": 44,
                            "xy": [
                                1205,
                                4535,
                                1205,
                                4705,
                                1375,
                                4705,
                                1375,
                                4535,
                                1205,
                                4535
                            ]
                        },
                        {
                            "type": "boundary",
                            "layer": 67,
                            "datatype": 44,
                            "xy": [
                                1205,
                                6215,
                                1205,
                                6385,
                                1375,
                                6385,
                                1375,
                                6215,
                                1205,
                                6215
                            ]
                        },
                        {
                            "type": "boundary",
                            "layer": 67,
                            "datatype": 44,
                            "xy": [
                                1205,
                                10415,
                                1205,
                                10585,
                                1375,
                                10585,
                                1375,
                                10415,
                                1205,
                                10415
                            ]
                        },
                        {
                            "type": "boundary",
                            "layer": 67,
                            "datatype": 44,
                            "xy": [
                                1205,
                                12095,
                                1205,
                                12265,
                                1375,
                                12265,
                                1375,
                                12095,
                                1205,
                                12095
                            ]
                        },
                        {
                            "type": "boundary",
                            "layer": 67,
                            "datatype": 44,
                            "xy": [
                                1205,
                                16295,
                                1205,
                                16465,
                                1375,
                                16465,
                                1375,
                                16295,
                                1205,
                                16295
                            ]
                        },
                        {
                            "type": "boundary",
                            "layer": 67,
                            "datatype": 44,
                            "xy": [
                                1205,
                                18395,
                                1205,
                                18565,
                                1375,
                                18565,
                                1375,
                                18395,
                                1205,
                                18395
                            ]
                        },
                        {
                            "type": "boundary",
                            "layer": 67,
                            "datatype": 44,
                            "xy": [
                                775,
                                755,
                                775,
                                925,
                                945,
                                925,
                                945,
                                755,
                                775,
                                755
                            ]
                        },
                        {
                            "type": "boundary",
                            "layer": 67,
                            "datatype": 44,
                            "xy": [
                                775,
                                6635,
                                775,
                                6805,
                                945,
                                6805,
                                945,
                                6635,
                                775,
                                6635
                            ]
                        },
                        {
                            "type": "boundary",
                            "layer": 67,
                            "datatype": 44,
                            "xy": [
                                775,
                                12515,
                                775,
                                12685,
                                945,
                                12685,
                                945,
                                12515,
                                775,
                                12515
                            ]
                        },
                        {
                            "type": "boundary",
                            "layer": 67,
                            "datatype": 44,
                            "xy": [
                                1635,
                                755,
                                1635,
                                925,
                                1805,
                                925,
                                1805,
                                755,
                                1635,
                                755
                            ]
                        },
                        {
                            "type": "boundary",
                            "layer": 67,
                            "datatype": 44,
                            "xy": [
                                1635,
                                6635,
                                1635,
                                6805,
                                1805,
                                6805,
                                1805,
                                6635,
                                1635,
                                6635
                            ]
                        },
                        {
                            "type": "boundary",
                            "layer": 67,
                            "datatype": 44,
                            "xy": [
                                1635,
                                12515,
                                1635,
                                12685,
                                1805,
                                12685,
                                1805,
                                12515,
                                1635,
                                12515
                            ]
                        },
                        {
                            "type": "boundary",
                            "layer": 69,
                            "datatype": 20,
                            "xy": [
                                1150,
                                260,
                                1150,
                                16540,
                                1430,
                                16540,
                                1430,
                                260,
                                1150,
                                260
                            ]
                        },
                        {
                            "type": "boundary",
                            "layer": 69,
                            "datatype": 20,
                            "xy": [
                                1580,
                                680,
                                1580,
                                18640,
                                1860,
                                18640,
                                1860,
                                680,
                                1580,
                                680
                            ]
                        },
                        {
                            "type": "boundary",
                            "layer": 68,
                            "datatype": 44,
                            "xy": [
                                1215,
                                345,
                                1215,
                                495,
                                1365,
                                495,
                                1365,
                                345,
                                1215,
                                345
                            ]
                        },
                        {
                            "type": "boundary",
                            "layer": 68,
                            "datatype": 44,
                            "xy": [
                                1215,
                                4545,
                                1215,
                                4695,
                                1365,
                                4695,
                                1365,
                                4545,
                                1215,
                                4545
                            ]
                        },
                        {
                            "type": "boundary",
                            "layer": 68,
                            "datatype": 44,
                            "xy": [
                                1215,
                                6225,
                                1215,
                                6375,
                                1365,
                                6375,
                                1365,
                                6225,
                                1215,
                                6225
                            ]
                        },
                        {
                            "type": "boundary",
                            "layer": 68,
                            "datatype": 44,
                            "xy": [
                                1215,
                                10425,
                                1215,
                                10575,
                                1365,
                                10575,
                                1365,
                                10425,
                                1215,
                                10425
                            ]
                        },
                        {
                            "type": "boundary",
                            "layer": 68,
                            "datatype": 44,
                            "xy": [
                                1215,
                                12105,
                                1215,
                                12255,
                                1365,
                                12255,
                                1365,
                                12105,
                                1215,
                                12105
                            ]
                        },
                        {
                            "type": "boundary",
                            "layer": 68,
                            "datatype": 44,
                            "xy": [
                                1215,
                                16305,
                                1215,
                                16455,
                                1365,
                                16455,
                                1365,
                                16305,
                                1215,
                                16305
                            ]
                        },
                        {
                            "type": "boundary",
                            "layer": 68,
                            "datatype": 44,
                            "xy": [
                                1645,
                                765,
                                1645,
                                915,
                                1795,
                                915,
                                1795,
                                765,
                                1645,
                                765
                            ]
                        },
                        {
                            "type": "boundary",
                            "layer": 68,
                            "datatype": 44,
                            "xy": [
                                1645,
                                6645,
                                1645,
                                6795,
                                1795,
                                6795,
                                1795,
                                6645,
                                1645,
                                6645
                            ]
                        },
                        {
                            "type": "boundary",
                            "layer": 68,
                            "datatype": 44,
                            "xy": [
                                1645,
                                12525,
                                1645,
                                12675,
                                1795,
                                12675,
                                1795,
                                12525,
                                1645,
                                12525
                            ]
                        },
                        {
                            "type": "boundary",
                            "layer": 68,
                            "datatype": 44,
                            "xy": [
                                1645,
                                18405,
                                1645,
                                18555,
                                1795,
                                18555,
                                1795,
                                18405,
                                1645,
                                18405
                            ]
                        },
                        {
                            "type": "boundary",
                            "layer": 66,
                            "datatype": 20,
                            "xy": [
                                1000,
                                1260,
                                1000,
                                4620,
                                1150,
                                4620,
                                1150,
                                1260,
                                1000,
                                1260
                            ]
                        },
                        {
                            "type": "boundary",
                            "layer": 66,
                            "datatype": 20,
                            "xy": [
                                1000,
                                7140,
                                1000,
                                10500,
                                1150,
                                10500,
                                1150,
                                7140,
                                1000,
                                7140
                            ]
                        },
                        {
                            "type": "boundary",
                            "layer": 66,
                            "datatype": 20,
                            "xy": [
                                1000,
                                13020,
                                1000,
                                16380,
                                1150,
                                16380,
                                1150,
                                13020,
                                1000,
                                13020
                            ]
                        },
                        {
                            "type": "boundary",
                            "layer": 66,
                            "datatype": 20,
                            "xy": [
                                1430,
                                1260,
                                1430,
                                4620,
                                1580,
                                4620,
                                1580,
                                1260,
                                1430,
                                1260
                            ]
                        },
                        {
                            "type": "boundary",
                            "layer": 66,
                            "datatype": 20,
                            "xy": [
                                1430,
                                7140,
                                1430,
                                10500,
                                1580,
                                10500,
                                1580,
                                7140,
                                1430,
                                7140
                            ]
                        },
                        {
                            "type": "boundary",
                            "layer": 66,
                            "datatype": 20,
                            "xy": [
                                1430,
                                13020,
                                1430,
                                16380,
                                1580,
                                16380,
                                1580,
                                13020,
                                1430,
                                13020
                            ]
                        },
                        {
                            "type": "boundary",
                            "layer": 66,
                            "datatype": 20,
                            "xy": [
                                1000,
                                4485,
                                1000,
                                4755,
                                1580,
                                4755,
                                1580,
                                4485,
                                1000,
                                4485
                            ]
                        },
                        {
                            "type": "boundary",
                            "layer": 66,
                            "datatype": 20,
                            "xy": [
                                1000,
                                10365,
                                1000,
                                10635,
                                1580,
                                10635,
                                1580,
                                10365,
                                1000,
                                10365
                            ]
                        },
                        {
                            "type": "boundary",
                            "layer": 66,
                            "datatype": 20,
                            "xy": [
                                1000,
                                16245,
                                1000,
                                16515,
                                1580,
                                16515,
                                1580,
                                16245,
                                1000,
                                16245
                            ]
                        },
                        {
                            "type": "boundary",
                            "layer": 65,
                            "datatype": 20,
                            "xy": [
                                735,
                                2625,
                                735,
                                3045,
                                1845,
                                3045,
                                1845,
                                2625,
                                735,
                                2625
                            ]
                        },
                        {
                            "type": "boundary",
                            "layer": 65,
                            "datatype": 20,
                            "xy": [
                                735,
                                8505,
                                735,
                                8925,
                                1845,
                                8925,
                                1845,
                                8505,
                                735,
                                8505
                            ]
                        },
                        {
                            "type": "boundary",
                            "layer": 65,
                            "datatype": 20,
                            "xy": [
                                735,
                                14385,
                                735,
                                14805,
                                1845,
                                14805,
                                1845,
                                14385,
                                735,
                                14385
                            ]
                        },
                        {
                            "type": "boundary",
                            "layer": 65,
                            "datatype": 44,
                            "xy": [
                                1205,
                                17920,
                                1205,
                                19040,
                                1375,
                                19040,
                                1375,
                                17920,
                                1205,
                                17920
                            ]
                        },
                        {
                            "type": "boundary",
                            "layer": 66,
                            "datatype": 44,
                            "xy": [
                                1205,
                                2705,
                                1205,
                                2875,
                                1375,
                                2875,
                                1375,
                                2705,
                                1205,
                                2705
                            ]
                        },
                        {
                            "type": "boundary",
                            "layer": 66,
                            "datatype": 44,
                            "xy": [
                                1205,
                                4535,
                                1205,
                                4705,
                                1375,
                                4705,
                                1375,
                                4535,
                                1205,
                                4535
                            ]
                        },
                        {
                            "type": "boundary",
                            "layer": 66,
                            "datatype": 44,
                            "xy": [
                                1205,
                                8585,
                                1205,
                                8755,
                                1375,
                                8755,
                                1375,
                                8585,
                                1205,
                                8585
                            ]
                        },
                        {
                            "type": "boundary",
                            "layer": 66,
                            "datatype": 44,
                            "xy": [
                                1205,
                                10415,
                                1205,
                                10585,
                                1375,
                                10585,
                                1375,
                                10415,
                                1205,
                                10415
                            ]
                        },
                        {
                            "type": "boundary",
                            "layer": 66,
                            "datatype": 44,
                            "xy": [
                                1205,
                                14465,
                                1205,
                                14635,
                                1375,
                                14635,
                                1375,
                                14465,
                                1205,
                                14465
                            ]
                        },
                        {
                            "type": "boundary",
                            "layer": 66,
                            "datatype": 44,
                            "xy": [
                                1205,
                                16295,
                                1205,
                                16465,
                                1375,
                                16465,
                                1375,
                                16295,
                                1205,
                                16295
                            ]
                        },
                        {
                            "type": "boundary",
                            "layer": 66,
                            "datatype": 44,
                            "xy": [
                                1205,
                                18395,
                                1205,
                                18565,
                                1375,
                                18565,
                                1375,
                                18395,
                                1205,
                                18395
                            ]
                        },
                        {
                            "type": "boundary",
                            "layer": 66,
                            "datatype": 44,
                            "xy": [
                                1205,
                                18395,
                                1205,
                                18565,
                                1375,
                                18565,
                                1375,
                                18395,
                                1205,
                                18395
                            ]
                        },
                        {
                            "type": "boundary",
                            "layer": 66,
                            "datatype": 44,
                            "xy": [
                                1205,
                                18395,
                                1205,
                                18565,
                                1375,
                                18565,
                                1375,
                                18395,
                                1205,
                                18395
                            ]
                        },
                        {
                            "type": "boundary",
                            "layer": 66,
                            "datatype": 44,
                            "xy": [
                                775,
                                2705,
                                775,
                                2875,
                                945,
                                2875,
                                945,
                                2705,
                                775,
                                2705
                            ]
                        },
                        {
                            "type": "boundary",
                            "layer": 66,
                            "datatype": 44,
                            "xy": [
                                775,
                                8585,
                                775,
                                8755,
                                945,
                                8755,
                                945,
                                8585,
                                775,
                                8585
                            ]
                        },
                        {
                            "type": "boundary",
                            "layer": 66,
                            "datatype": 44,
                            "xy": [
                                775,
                                14465,
                                775,
                                14635,
                                945,
                                14635,
                                945,
                                14465,
                                775,
                                14465
                            ]
                        },
                        {
                            "type": "boundary",
                            "layer": 66,
                            "datatype": 44,
                            "xy": [
                                1635,
                                2705,
                                1635,
                                2875,
                                1805,
                                2875,
                                1805,
                                2705,
                                1635,
                                2705
                            ]
                        },
                        {
                            "type": "boundary",
                            "layer": 66,
                            "datatype": 44,
                            "xy": [
                                1635,
                                8585,
                                1635,
                                8755,
                                1805,
                                8755,
                                1805,
                                8585,
                                1635,
                                8585
                            ]
                        },
                        {
                            "type": "boundary",
                            "layer": 66,
                            "datatype": 44,
                            "xy": [
                                1635,
                                14465,
                                1635,
                                14635,
                                1805,
                                14635,
                                1805,
                                14465,
                                1635,
                                14465
                            ]
                        },
                        {
                            "type": "boundary",
                            "layer": 100,
                            "datatype": 5,
                            "xy": [
                                0,
                                0,
                                0,
                                19320,
                                2580,
                                19320,
                                2580,
                                0,
                                0,
                                0
                            ]
                        }
                    ]
                }
            ]
        }
    ]
}